jwtgen/__init__.py
jwtgen/cli.py
jwtgen/jwt_utils.py
jwtgen/version.py
jwtgen-0.1.3.dist-info/LICENSE
jwtgen-0.1.3.dist-info/METADATA
jwtgen-0.1.3.dist-info/WHEEL
jwtgen-0.1.3.dist-info/entry_points.txt
jwtgen-0.1.3.dist-info/RECORD
